[
  {
    "nome": "Arrocha Safadão - Salvador Produções",
    "arquivo": "eventos/ArrochaSafadao_Salvador Produções e Entretenimento.pdf"
  },
  {
    "nome": "Baile Santinha - Salvador Produções",
    "arquivo": "eventos/BaileSantinhaEventos_Salvador Produções e Entretenimento.pdf"
  },
  {
    "nome": "Bloco Timbalada - Salvador Produções",
    "arquivo": "eventos/BlocoTimbalada_Salvador Produções e Entretenimento.pdf"
  },
  {
    "nome": "Camarote Arrocha PF - Salvador Produções",
    "arquivo": "eventos/CamaroteArrochaPFEventos_Salvador Produções e Entretenimento.pdf"
  },
  {
    "nome": "Camarote DVD Pabllo - Salvador Produções",
    "arquivo": "eventos/CamaroteDVDPablloEventos_Salvador Produções e Entretenimento.pdf"
  },
  {
    "nome": "Camarote Glamour - Salvador Produções",
    "arquivo": "eventos/CamaroteGlamour_Salvador Produções e Entretenimento.pdf"
  },
  {
    "nome": "MNB Record - Salvador Produções",
    "arquivo": "eventos/MNBRecordEventos_Salvador Produções e Entretenimento.pdf"
  },
  {
    "nome": "Magaconvidados - Axe40anos",
    "arquivo": "eventos/MagaconvidadEventos_axe40anos_Salvador Produções e Entretenimento.pdf"
  },
  {
    "nome": "Ressaca Timbalada - Salvador Produções",
    "arquivo": "eventos/RessacaTimbaladaEventos_Salvador Produções e Entretenimento.pdf"
  },
  {
    "nome": "Timbalada Ensaio 09/02 - Salvador Produções",
    "arquivo": "eventos/TimbaladaEnsaio0902_Salvador Produções e Entretenimento.pdf"
  },
  {
    "nome": "Timbalada Ensaio DVD - Salvador Produções",
    "arquivo": "eventos/TimbaladaEnsaioDVDEventos_Salvador Produções e Entretenimento.pdf"
  },
  {
    "nome": "Timbalada Eventos 05/01 - Salvador Produções",
    "arquivo": "eventos/TimbaladaEventos0501_Salvador Produções e Entretenimento.pdf"
  }
]
